pymodaq_plugins_daqmx/__init__.py
pymodaq_plugins_daqmx/utils.py
pymodaq_plugins_daqmx/daq_move_plugins/__init__.py
pymodaq_plugins_daqmx/daq_move_plugins/daq_move_DAQmx.py
pymodaq_plugins_daqmx/daq_move_plugins/daq_move_DAQmx_MultipleScannerControl.py
pymodaq_plugins_daqmx/daq_move_plugins/daq_move_DAQmx_ScannerControl.py
pymodaq_plugins_daqmx/daq_viewer_plugins/__init__.py
pymodaq_plugins_daqmx/daq_viewer_plugins/plugins_0D/__init__.py
pymodaq_plugins_daqmx/daq_viewer_plugins/plugins_0D/daq_0Dviewer_DAQmx_PLcounter.py
pymodaq_plugins_daqmx/daq_viewer_plugins/plugins_0D/daq_0Dviewer_NIDAQmx.py
pymodaq_plugins_daqmx/daq_viewer_plugins/plugins_1D/__init__.py
pymodaq_plugins_daqmx/daq_viewer_plugins/plugins_1D/daq_1Dviewer_DAQmx.py
pymodaq_plugins_daqmx/daq_viewer_plugins/plugins_2D/__init__.py
pymodaq_plugins_daqmx/daq_viewer_plugins/plugins_ND/__init__.py
pymodaq_plugins_daqmx/hardware/__init__.py
pymodaq_plugins_daqmx/hardware/national_instruments/NIDAQmx_Viewer.py
pymodaq_plugins_daqmx/hardware/national_instruments/NIDAQmx_base.py
pymodaq_plugins_daqmx/hardware/national_instruments/__init__.py
pymodaq_plugins_daqmx/hardware/national_instruments/daq_NIDAQmx.py
pymodaq_plugins_daqmx/hardware/national_instruments/daqmx.py
pymodaq_plugins_daqmx/hardware/national_instruments/daqmx_objects.py
pymodaq_plugins_daqmx/hardware/national_instruments/daqmxni.py
pymodaq_plugins_daqmx/resources/__init__.py
pymodaq_plugins_daqmx/resources/config_template.toml
pymodaq_plugins_daqmx-1.0.1.dist-info/METADATA
pymodaq_plugins_daqmx-1.0.1.dist-info/WHEEL
pymodaq_plugins_daqmx-1.0.1.dist-info/entry_points.txt
pymodaq_plugins_daqmx-1.0.1.dist-info/licenses/LICENSE
pymodaq_plugins_daqmx-1.0.1.dist-info/RECORD
