Metadata-Version: 2.4
Name: pymodaq_plugins_daqmx
Version: 1.0.1
Summary: Hardware plugins for PyMoDAQ using the NiDAQmx framework (nidaq wrapper)
Project-URL: Homepage, https://pymodaq.cnrs.fr
Project-URL: Documentation , https://pymodaq.cnrs.fr
Project-URL: Repository , https://github.com/PyMoDAQ/pymodaq_plugins_daqmx
Author-email: Sébastien Weber <sebastien.weber@cemes.fr>, Sébastien Guerrero <sebastien.guerrero@insa-lyon.fr>
Maintainer-email: Sébastien Weber <sebastien.weber@cemes.fr>, Sébastien Guerrero <sebastien.guerrero@insa-lyon.fr>
License: The MIT License (MIT)
License-File: LICENSE
Classifier: Development Status :: 5 - Production/Stable
Classifier: Intended Audience :: Science/Research
Classifier: License :: OSI Approved :: MIT License
Classifier: Natural Language :: English
Classifier: Operating System :: OS Independent
Classifier: Programming Language :: Python :: 3.8
Classifier: Programming Language :: Python :: 3.9
Classifier: Programming Language :: Python :: 3.10
Classifier: Programming Language :: Python :: 3.11
Classifier: Topic :: Scientific/Engineering :: Human Machine Interfaces
Classifier: Topic :: Scientific/Engineering :: Visualization
Classifier: Topic :: Software Development :: Libraries :: Python Modules
Classifier: Topic :: Software Development :: User Interfaces
Requires-Python: >=3.8
Requires-Dist: aenum
Requires-Dist: nidaqmx
Requires-Dist: pydaqmx
Requires-Dist: pymodaq>=4.4
